mystracher/__init__.py
mystracher-0.2.dist-info/METADATA
mystracher-0.2.dist-info/WHEEL
mystracher-0.2.dist-info/top_level.txt
mystracher-0.2.dist-info/RECORD
