Metadata-Version: 2.1
Name: mystracher
Version: 0.2
Summary: A structure / Grammar checker for English - a Python wrapper 3.7 for ATD (After The Dateline)
Home-page: https://github.com/Shahabks/mystracher
Author: Shahab Sabahi
Author-email: mysoltechnologyai@gmail.com
License: MIT
Keywords: praat speech signal processing phonetics
Platform: UNKNOWN
Classifier: Intended Audience :: Education
Classifier: Topic :: Utilities
Classifier: License :: OSI Approved :: MIT License
Classifier: Programming Language :: Python :: 3.7
